{"GlobalPropertiesHash":"Guirh4C3PleTnUPHX3b2bKhM8Fx0cr1pOgGhEobjR1A=","FingerprintPatternsHash":"gq3WsqcKBUGTSNle7RKKyXRIwh7M8ccEqOqYvIzoM04=","PropertyOverridesHash":"8ZRc1sGeVrPBx4lD717BgRaQekyh78QKV9SKsdt638U=","InputHashes":["mqxO\u002Bn17Nrg0hvYmlzy2y0FbIu3ztTjd\u002BzQt8kO8eOc=","ZRWO2z/f6K83JpYvmxUrAFJOsBuTBBXgF1a2rLHN6Jo=","H1\u002BDW3zzylFgGpOc7f/V16lCTsn8m6yqA2GLeTpIgDA=","GzBPTgS8RzdPCczYg/0WvmKIFpyKv94BFFLF3voiFv0=","qJuR0YVRrkxFc1ahyWh/9MsgqdTAuvAVLZVqSJkEVFE=","XeiLL9BwEAK2e\u002BXXqTJhra5SGKUv7K\u002Btg98Pi\u002Brku2o=","QyaFhT/gl/u3JUKARr5SRwNKhKULPD\u002BvS7DecvxFHQE=","wj\u002B6wzhJwjXzniwA1L/mJCORDX9t0laKHv6nlQsI7qI=","RdsziLtsxqnkZPsntl4eo0O5MPwmX7lakcMoB/fSngQ=","zCuctdLJ3HV9BlwbGrWXTUvJgEFwcuHns2jekYQ0twE=","RkBhuDxN5yzfVaB0fd\u002BCutlC0rW4egcWDhof5Yi6a6c=","o1t6yxjg0r3YhhrWSVwOZMH05t7KauHnri84pghExjQ=","59T0etMBYc8/6dIIGoW7AZR6\u002B/PvGMRPlDeHr24sAC8=","1UYE0KN0ex8tKWCdAcPPYT1lKWK0caNMHAMCIUh4x/8=","9f8RkL41J4zxwpa8i1BQymh0bSI22bcaB8669seBUAs=","6Nvus\u002BdLVuAePGryTIASY\u002BCCy9t9dQzZVyYWGVrrsyI="],"CachedAssets":{"mqxO\u002Bn17Nrg0hvYmlzy2y0FbIu3ztTjd\u002BzQt8kO8eOc=":{"Identity":"C:\\2025\\PROYECTOS_FRONT\\FrontendBlazorApi\\wwwroot\\app.css","SourceId":"FrontendBlazorApi","SourceType":"Discovered","ContentRoot":"C:\\2025\\PROYECTOS_FRONT\\FrontendBlazorApi\\wwwroot\\","BasePath":"_content/FrontendBlazorApi","RelativePath":"app#[.{fingerprint}]?.css","AssetKind":"All","AssetMode":"All","AssetRole":"Primary","AssetMergeBehavior":null,"AssetMergeSource":"","RelatedAsset":null,"AssetTraitName":null,"AssetTraitValue":null,"Fingerprint":"da95v2qkru","Integrity":"u9qEka1auR7E3rd3/8/j8hkQdSOYj9bRJ4nYiFDR1sE=","CopyToOutputDirectory":"Never","CopyToPublishDirectory":"PreserveNewest","OriginalItemSpec":"wwwroot\\app.css","FileLength":2591,"LastWriteTime":"2025-09-26T18:29:09+00:00"},"ZRWO2z/f6K83JpYvmxUrAFJOsBuTBBXgF1a2rLHN6Jo=":{"Identity":"C:\\2025\\PROYECTOS_FRONT\\FrontendBlazorApi\\wwwroot\\bootstrap\\bootstrap.min.css","SourceId":"FrontendBlazorApi","SourceType":"Discovered","ContentRoot":"C:\\2025\\PROYECTOS_FRONT\\FrontendBlazorApi\\wwwroot\\","BasePath":"_content/FrontendBlazorApi","RelativePath":"bootstrap/bootstrap.min#[.{fingerprint}]?.css","AssetKind":"All","AssetMode":"All","AssetRole":"Primary","AssetMergeBehavior":null,"AssetMergeSource":"","RelatedAsset":null,"AssetTraitName":null,"AssetTraitValue":null,"Fingerprint":"bpk8xqwxhs","Integrity":"z8OR40MowJ8GgK6P89Y\u002BhiJK5\u002BcclzFHzLhFQLL92bg=","CopyToOutputDirectory":"Never","CopyToPublishDirectory":"PreserveNewest","OriginalItemSpec":"wwwroot\\bootstrap\\bootstrap.min.css","FileLength":162720,"LastWriteTime":"2025-09-26T18:29:09+00:00"},"H1\u002BDW3zzylFgGpOc7f/V16lCTsn8m6yqA2GLeTpIgDA=":{"Identity":"C:\\2025\\PROYECTOS_FRONT\\FrontendBlazorApi\\wwwroot\\bootstrap\\bootstrap.min.css.map","SourceId":"FrontendBlazorApi","SourceType":"Discovered","ContentRoot":"C:\\2025\\PROYECTOS_FRONT\\FrontendBlazorApi\\wwwroot\\","BasePath":"_content/FrontendBlazorApi","RelativePath":"bootstrap/bootstrap.min.css#[.{fingerprint}]?.map","AssetKind":"All","AssetMode":"All","AssetRole":"Primary","AssetMergeBehavior":null,"AssetMergeSource":"","RelatedAsset":null,"AssetTraitName":null,"AssetTraitValue":null,"Fingerprint":"8inm30yfxf","Integrity":"gBwg2tmA0Ci2u54gMF1jNCVku6vznarkLS6D76htNNQ=","CopyToOutputDirectory":"Never","CopyToPublishDirectory":"PreserveNewest","OriginalItemSpec":"wwwroot\\bootstrap\\bootstrap.min.css.map","FileLength":449111,"LastWriteTime":"2025-09-26T18:29:09+00:00"},"GzBPTgS8RzdPCczYg/0WvmKIFpyKv94BFFLF3voiFv0=":{"Identity":"C:\\2025\\PROYECTOS_FRONT\\FrontendBlazorApi\\wwwroot\\favicon.png","SourceId":"FrontendBlazorApi","SourceType":"Discovered","ContentRoot":"C:\\2025\\PROYECTOS_FRONT\\FrontendBlazorApi\\wwwroot\\","BasePath":"_content/FrontendBlazorApi","RelativePath":"favicon#[.{fingerprint}]?.png","AssetKind":"All","AssetMode":"All","AssetRole":"Primary","AssetMergeBehavior":null,"AssetMergeSource":"","RelatedAsset":null,"AssetTraitName":null,"AssetTraitValue":null,"Fingerprint":"ifv42okdf2","Integrity":"4mWsDy3aHl36ZbGt8zByK7Pvd4kRUoNgTYzRnwmPHwg=","CopyToOutputDirectory":"Never","CopyToPublishDirectory":"PreserveNewest","OriginalItemSpec":"wwwroot\\favicon.png","FileLength":1148,"LastWriteTime":"2025-09-26T18:29:09+00:00"}},"CachedCopyCandidates":{}}